visier_api_analytic_model/__init__.py
visier_api_analytic_model/py.typed
visier_api_analytic_model/api/__init__.py
visier_api_analytic_model/api/concepts_v2_api.py
visier_api_analytic_model/api/data_model_api.py
visier_api_analytic_model/api/object_configuration_api.py
visier_api_analytic_model/models/__init__.py
visier_api_analytic_model/models/dataservices_common_dimension_member_reference_dto.py
visier_api_analytic_model/models/dataservices_common_member_values_dto.py
visier_api_analytic_model/models/dataservices_datamodel_aggregation_type_option_dto.py
visier_api_analytic_model/models/dataservices_datamodel_aggregation_type_parameter_dto.py
visier_api_analytic_model/models/dataservices_datamodel_analytic_object_dto.py
visier_api_analytic_model/models/dataservices_datamodel_analytic_objects_dto.py
visier_api_analytic_model/models/dataservices_datamodel_currencies_dto.py
visier_api_analytic_model/models/dataservices_datamodel_currency_dto.py
visier_api_analytic_model/models/dataservices_datamodel_currency_rate_dto.py
visier_api_analytic_model/models/dataservices_datamodel_currency_rates_dto.py
visier_api_analytic_model/models/dataservices_datamodel_dimension_dto.py
visier_api_analytic_model/models/dataservices_datamodel_dimension_mapping_validation_dto.py
visier_api_analytic_model/models/dataservices_datamodel_dimension_mapping_validation_execution_dto.py
visier_api_analytic_model/models/dataservices_datamodel_dimension_reference_dto.py
visier_api_analytic_model/models/dataservices_datamodel_dimensions_dto.py
visier_api_analytic_model/models/dataservices_datamodel_level_dto.py
visier_api_analytic_model/models/dataservices_datamodel_member_dto.py
visier_api_analytic_model/models/dataservices_datamodel_member_parameter_definition_dto.py
visier_api_analytic_model/models/dataservices_datamodel_members_dto.py
visier_api_analytic_model/models/dataservices_datamodel_metric_dto.py
visier_api_analytic_model/models/dataservices_datamodel_metrics_dto.py
visier_api_analytic_model-22222222.99201.1906.dist-info/METADATA
visier_api_analytic_model-22222222.99201.1906.dist-info/WHEEL
visier_api_analytic_model-22222222.99201.1906.dist-info/top_level.txt
visier_api_analytic_model-22222222.99201.1906.dist-info/RECORD
